Metadata-Version: 2.1
Name: Kvsqlite
Version: 0.1.1
Summary: Easy-to-use asynchronous key-value database backed by sqlite3.
Home-page: https://github.com/AYMENJD/kvsqlite
Author: AYMEN Mohammed
Author-email: let.me.code.safe@gmail.com
License: MIT
Project-URL: Source, https://github.com/AYMENJD/kvsqlite
Project-URL: Tracker, https://github.com/AYMENJD/kvsqlite/issues
Project-URL: Documentation, https://kvsqlite.rtfd.io/
Keywords: asyncio,sqlite,sqlite3,key-value,database,redis
Requires-Python: >=3.8
License-File: LICENSE
